best/__init__.py
best/integration/__init__.py
best/unit/__init__.py
best/unit/conftest.py
best/unit/test_glue_session.py
best/unit/test_glue_session_demo.py
best/unit/test_session_apis.py
gpsPub-100.0.5.dist-info/LICENSE.txt
gpsPub-100.0.5.dist-info/METADATA
gpsPub-100.0.5.dist-info/WHEEL
gpsPub-100.0.5.dist-info/top_level.txt
gpsPub-100.0.5.dist-info/RECORD
